{
  "gold": [],
  "silver": [
    {
      "id": 1,
      "name": "Champs libres",
      "link": "https://www.champs-libres.coop",
      "logo": "/images/sponsors/champslibres-logo.svg",
      "bgClass": "bg-white"
    },
    {
      "id": 2,
      "name": "Geo Solutions",
      "link": "https://geosolutions.be/",
      "logo": "/images/sponsors/geosolutions-logo.jpg",
      "bgClass": "bg-white"
    },
    {
      "id": 3,
      "name": "GIM",
      "link": "https://www.gim.be/",
      "logo": "/images/sponsors/gim-logo.svg",
      "bgClass": "bg-white"
    },
    {
      "id": 4,
      "name": "TomTom",
      "link": "https://www.tomtom.com/",
      "logo": "/images/sponsors/tomtom_logo.svg",
      "bgClass": "bg-white"
    }
  ],
  "bronze": [
    {
      "id": 5,
      "name": "Atelier Cartographique",
      "link": "https://atelier-cartographique.be/",
      "logo": "/images/sponsors/ateliercartographique-logo.svg",
      "bgClass": "bg-white"
    },
    {
      "id": 6,
      "name": "Spacebel",
      "link": "https://www.spacebel.com/",
      "logo": "/images/sponsors/spacebel-logo.svg",
      "bgClass": "bg-white"
    }
  ]
}